<?xml version="1.0" encoding="utf-8"?>
<cms.webpageitem>
  <WebPageItemContentItemID>
    <CodeName>12-910q9zxz</CodeName>
    <GUID>086afffa-13f2-43a9-ba1e-c23f3142a3b0</GUID>
    <ObjectType>cms.contentitem</ObjectType>
  </WebPageItemContentItemID>
  <WebPageItemGUID>20c41a91-d7cf-4c4c-9b46-8d95d247bf03</WebPageItemGUID>
  <WebPageItemName>12-910q9zxz</WebPageItemName>
  <WebPageItemOrder>1</WebPageItemOrder>
  <WebPageItemParentID>
    <CodeName>2024-eunzwcnn</CodeName>
    <GUID>02b1fd7c-2266-4c31-9a73-b865fdd060e0</GUID>
    <ObjectType>cms.webpageitem</ObjectType>
  </WebPageItemParentID>
  <WebPageItemTreePath>/Blog/Posts-djbze2fn/2024/12</WebPageItemTreePath>
  <WebPageItemWebsiteChannelID>
    <GUID>9ca57e0f-969f-43be-91d3-6c45659316bd</GUID>
    <ObjectType>cms.websitechannel</ObjectType>
    <Parent>
      <CodeName>devnet</CodeName>
      <GUID>4f636110-fd4a-4905-83e6-998752c2b2c2</GUID>
      <ObjectType>cms.channel</ObjectType>
    </Parent>
  </WebPageItemWebsiteChannelID>
</cms.webpageitem>