<?xml version="1.0" encoding="utf-8"?>
<cms.webpageurlpath>
  <WebPageUrlPath>
    <![CDATA[Q-and-A/q/Is-there-a-new-Xperience-by-Kentico-tutorial-0b0705a7]]>
  </WebPageUrlPath>
  <WebPageUrlPathContentLanguageID>
    <CodeName>en-US</CodeName>
    <GUID>6c743a9e-8a63-425b-bef6-756c12c1bbf5</GUID>
    <ObjectType>cms.contentlanguage</ObjectType>
  </WebPageUrlPathContentLanguageID>
  <WebPageUrlPathGUID>e434e331-cfaa-49da-b097-e1d354b200fd</WebPageUrlPathGUID>
  <WebPageUrlPathHash>
    <![CDATA[703D52F8BE296D87E073B77D04061B1E9FD0506AE4A66961980154D1F3DCF6AC]]>
  </WebPageUrlPathHash>
  <WebPageUrlPathIsCanonical>True</WebPageUrlPathIsCanonical>
  <WebPageUrlPathIsDraft>False</WebPageUrlPathIsDraft>
  <WebPageUrlPathIsLatest>True</WebPageUrlPathIsLatest>
  <WebPageUrlPathType>0</WebPageUrlPathType>
  <WebPageUrlPathWebPageItemID>
    <CodeName>Is-there-a-new-Xperience-by-Kentico-tutorial--0b0705a7-tysbut8z-localtest</CodeName>
    <GUID>b0d2783b-62ea-4a3e-beff-a7775d530739</GUID>
    <ObjectType>cms.webpageitem</ObjectType>
  </WebPageUrlPathWebPageItemID>
  <WebPageUrlPathWebsiteChannelID>
    <GUID>9ca57e0f-969f-43be-91d3-6c45659316bd</GUID>
    <ObjectType>cms.websitechannel</ObjectType>
    <Parent>
      <CodeName>devnet</CodeName>
      <GUID>4f636110-fd4a-4905-83e6-998752c2b2c2</GUID>
      <ObjectType>cms.channel</ObjectType>
    </Parent>
  </WebPageUrlPathWebsiteChannelID>
</cms.webpageurlpath>