<?xml version="1.0" encoding="utf-8"?>
<contentitemdata.kenticocommunity.imagecontent>
  <ContentItemDataCommonDataID>
    <GUID>7cff047b-9ea9-44fc-881f-236e9d3182fb</GUID>
    <ObjectType>cms.contentitemcommondata</ObjectType>
    <Parent>
      <CodeName>SeanG.WrightPhoto-xve68szd</CodeName>
      <GUID>be399de0-69f8-49b2-b292-777b06d34566</GUID>
      <ObjectType>cms.contentitem</ObjectType>
    </Parent>
  </ContentItemDataCommonDataID>
  <ContentItemDataGUID>52f7fb4a-328e-4b99-98c2-a9437cd42d25</ContentItemDataGUID>
  <ImageContentAsset>
    <![CDATA[{"Identifier":"9f61e1a4-d894-4922-b81c-a54170d45760","Name":"2023_headshot_head_small.webp","Extension":".webp","Size":11300,"Width":500,"Height":500,"LastModified":"2024-09-01T14:21:35.3226234Z"}]]>
  </ImageContentAsset>
</contentitemdata.kenticocommunity.imagecontent>