<?xml version="1.0" encoding="utf-8"?>
<contentitemdata.kenticocommunity.cardcontent>
  <CardContentListableItem>
    <![CDATA[[{"Identifier":"b1b050b2-06b9-4148-93cc-dca2a7f6fd66"}]]]>
  </CardContentListableItem>
  <CardContentUTMParameters>
    <![CDATA[{"ID":"bac44ba1-1147-4d4b-b4e4-1a65edb71162","Source":"","Medium":"","Campaign":"","Content":"blog","Term":"card"}]]>
  </CardContentUTMParameters>
  <CardContentWebpage>
    <![CDATA[[{"WebPageGuid":"f99c71a2-6dd2-4b60-b367-da94ff9c38c0"}]]]>
  </CardContentWebpage>
  <ContentItemDataCommonDataID>
    <GUID>643ef4b9-8d9b-45e9-a200-ddc0f5456503</GUID>
    <ObjectType>cms.contentitemcommondata</ObjectType>
    <Parent>
      <CodeName>KenticoCommunityPortalUpdate-MemberBadges-l47yi3ix</CodeName>
      <GUID>df298fb2-a218-4605-b88f-7671d7c85e75</GUID>
      <ObjectType>cms.contentitem</ObjectType>
    </Parent>
  </ContentItemDataCommonDataID>
  <ContentItemDataGUID>846eb3d5-a123-4b2a-b964-2326c5a6b7d3</ContentItemDataGUID>
</contentitemdata.kenticocommunity.cardcontent>