<?xml version="1.0" encoding="utf-8"?>
<contentitemdata.kenticocommunity.blogpostcontent>
  <BlogPostContentBlogType>
    <![CDATA[[{"Identifier":"0cb21dda-384b-4792-8e1b-41034f113d28"}]]]>
  </BlogPostContentBlogType>
  <ContentItemDataCommonDataID>
    <GUID>6e1e18f1-f637-4ecf-b04f-e1ad8618bf6b</GUID>
    <ObjectType>cms.contentitemcommondata</ObjectType>
    <Parent>
      <CodeName>EvolvingDancingGoatWithAgenticAISoftwareDevelopment-hno7bd9h</CodeName>
      <GUID>9b20fb1e-a34c-4daf-a795-286ad286f159</GUID>
      <ObjectType>cms.contentitem</ObjectType>
    </Parent>
  </ContentItemDataCommonDataID>
  <ContentItemDataGUID>6abc4a83-63c2-46a5-ad38-acda4ec77e10</ContentItemDataGUID>
</contentitemdata.kenticocommunity.blogpostcontent>