<?xml version="1.0" encoding="utf-8"?>
<cms.webpageurlpath>
  <WebPageUrlPath>Blog/Kentico-community-interview-Mike-Rahel</WebPageUrlPath>
  <WebPageUrlPathContentLanguageID>
    <CodeName>en-US</CodeName>
    <GUID>6c743a9e-8a63-425b-bef6-756c12c1bbf5</GUID>
    <ObjectType>cms.contentlanguage</ObjectType>
  </WebPageUrlPathContentLanguageID>
  <WebPageUrlPathGUID>fa807a05-eb5c-4a85-9c8f-aace500ef266</WebPageUrlPathGUID>
  <WebPageUrlPathHash>
    <![CDATA[D0D3C8ADD1E874A6F30F43030FD8735DAB217A033DF5A8941EB10F2D66FAAC59]]>
  </WebPageUrlPathHash>
  <WebPageUrlPathIsCanonical>True</WebPageUrlPathIsCanonical>
  <WebPageUrlPathIsDraft>False</WebPageUrlPathIsDraft>
  <WebPageUrlPathIsLatest>True</WebPageUrlPathIsLatest>
  <WebPageUrlPathType>0</WebPageUrlPathType>
  <WebPageUrlPathWebPageItemID>
    <CodeName>KenticoCommunityInterview_MikeRahel-hq7ddojk</CodeName>
    <GUID>4d4b42d2-f984-4556-b032-e8383349bc1c</GUID>
    <ObjectType>cms.webpageitem</ObjectType>
  </WebPageUrlPathWebPageItemID>
  <WebPageUrlPathWebsiteChannelID>
    <GUID>9ca57e0f-969f-43be-91d3-6c45659316bd</GUID>
    <ObjectType>cms.websitechannel</ObjectType>
    <Parent>
      <CodeName>devnet</CodeName>
      <GUID>4f636110-fd4a-4905-83e6-998752c2b2c2</GUID>
      <ObjectType>cms.channel</ObjectType>
    </Parent>
  </WebPageUrlPathWebsiteChannelID>
</cms.webpageurlpath>