<?xml version="1.0" encoding="utf-8"?>
<media.file>
  <FileCreatedByUserID>
    <CodeName>SeanW@kentico.com</CodeName>
    <GUID>dfbb939f-efca-409d-9ddc-613047fadcca</GUID>
    <ObjectType>cms.user</ObjectType>
  </FileCreatedByUserID>
  <FileCreatedWhen>2024-06-10 22:09:11Z</FileCreatedWhen>
  <FileDescription />
  <FileExtension>.webp</FileExtension>
  <FileGUID>d9af6f07-a325-4d12-9efe-b7a4f08ebbc9</FileGUID>
  <FileImageHeight>901</FileImageHeight>
  <FileImageWidth>1021</FileImageWidth>
  <FileLibraryID>
    <CodeName>qanda</CodeName>
    <GUID>99754695-d637-4339-97c6-4c48a4fa6e1d</GUID>
    <ObjectType>media.library</ObjectType>
  </FileLibraryID>
  <FileMimeType>image/webp</FileMimeType>
  <FileModifiedByUserID>
    <CodeName>SeanW@kentico.com</CodeName>
    <GUID>dfbb939f-efca-409d-9ddc-613047fadcca</GUID>
    <ObjectType>cms.user</ObjectType>
  </FileModifiedByUserID>
  <FileName>xperience-multi-project-architecture</FileName>
  <FilePath>xperience-multi-project-architecture.webp</FilePath>
  <FileSize>21064</FileSize>
  <FileTitle />
</media.file>