<?xml version="1.0" encoding="utf-8"?>
<contentitemdata.kenticocommunity.linkcontent>
  <ContentItemDataCommonDataID>
    <GUID>961b99d3-c33e-43f5-b7aa-dbf0017dc748</GUID>
    <ObjectType>cms.contentitemcommondata</ObjectType>
    <Parent>
      <CodeName>KenticoCommunitySlack-kvyzh6np</CodeName>
      <GUID>ea3c2e67-b69a-4eae-bc7b-a3497ef9f1c7</GUID>
      <ObjectType>cms.contentitem</ObjectType>
    </Parent>
  </ContentItemDataCommonDataID>
  <ContentItemDataGUID>51b15d66-aea6-4425-ab89-1ebb5242ce20</ContentItemDataGUID>
  <LinkContentLinkType />
  <LinkContentMemberID>0</LinkContentMemberID>
  <LinkContentPathOrURL>https://kentico-community.slack.com/</LinkContentPathOrURL>
  <LinkContentPublishedDate>0001-01-01 04:57:00Z</LinkContentPublishedDate>
</contentitemdata.kenticocommunity.linkcontent>