<?xml version="1.0" encoding="utf-8"?>
<contentitemdata.kenticocommunity.qandaquestionpage>
  <ContentItemDataCommonDataID>
    <GUID>09104055-c09e-4cff-985c-27e47aeacd64</GUID>
    <ObjectType>cms.contentitemcommondata</ObjectType>
    <Parent>
      <CodeName>Blog-Discussion-Test-blog-post-557af50b-jh06drc8-localtest</CodeName>
      <GUID>cc242b05-38b0-4854-b16b-cbe598e6e2be</GUID>
      <ObjectType>cms.contentitem</ObjectType>
    </Parent>
  </ContentItemDataCommonDataID>
  <ContentItemDataGUID>30680fb4-24cd-4a33-b369-88861f7af9dc</ContentItemDataGUID>
  <QAndAQuestionPageAcceptedAnswerDataGUID>00000000-0000-0000-0000-000000000000</QAndAQuestionPageAcceptedAnswerDataGUID>
  <QAndAQuestionPageAuthorMemberID>0</QAndAQuestionPageAuthorMemberID>
  <QAndAQuestionPageBlogPostPages>
    <![CDATA[[{"Identifier":"97f9f458-18d3-4e17-a592-91ac34a57d77"}]]]>
  </QAndAQuestionPageBlogPostPages>
  <QAndAQuestionPageContent>
<![CDATA[
Blog Post: [Test blog post](/blog/test-blog-post)

Continue discussions 🤗 on this blog post below.
]]>
  </QAndAQuestionPageContent>
  <QAndAQuestionPageDateCreated>2025-06-12 16:44:24Z</QAndAQuestionPageDateCreated>
  <QAndAQuestionPageDateModified>2025-06-12 16:44:24Z</QAndAQuestionPageDateModified>
  <QAndAQuestionPageDiscussionType>
    <![CDATA[[{"Identifier":"0a81201d-8daa-4a54-bcc1-320914635b8f"}]]]>
  </QAndAQuestionPageDiscussionType>
</contentitemdata.kenticocommunity.qandaquestionpage>