<?xml version="1.0" encoding="utf-8"?>
<cms.webpageitem>
  <WebPageItemContentItemID>
    <CodeName>Manage-multiple-websites-5d74fce9-o35bje6g</CodeName>
    <GUID>a4a9f40b-0d9e-477f-aeaa-604d6a5ea866</GUID>
    <ObjectType>cms.contentitem</ObjectType>
  </WebPageItemContentItemID>
  <WebPageItemGUID>c9006ddb-6ddb-4452-9533-aab30dc910cd</WebPageItemGUID>
  <WebPageItemName>Manage-multiple-websites-5d74fce9-o35bje6g</WebPageItemName>
  <WebPageItemOrder>23</WebPageItemOrder>
  <WebPageItemParentID>
    <CodeName>08-e9xq9ve1</CodeName>
    <GUID>2f9ce8df-b371-47e8-8bb8-36e27ad7f311</GUID>
    <ObjectType>cms.webpageitem</ObjectType>
  </WebPageItemParentID>
  <WebPageItemTreePath>
    <![CDATA[/Q-and-A/Questions/2025/08/Manage-multiple-websites-5d74fce9]]>
  </WebPageItemTreePath>
  <WebPageItemWebsiteChannelID>
    <GUID>9ca57e0f-969f-43be-91d3-6c45659316bd</GUID>
    <ObjectType>cms.websitechannel</ObjectType>
    <Parent>
      <CodeName>devnet</CodeName>
      <GUID>4f636110-fd4a-4905-83e6-998752c2b2c2</GUID>
      <ObjectType>cms.channel</ObjectType>
    </Parent>
  </WebPageItemWebsiteChannelID>
</cms.webpageitem>