<?xml version="1.0" encoding="utf-8"?>
<contentitemdata.kenticocommunity.linkcontent>
  <ContentItemDataCommonDataID>
    <GUID>7e65b192-298d-4a86-a4ff-5185503dba89</GUID>
    <ObjectType>cms.contentitemcommondata</ObjectType>
    <Parent>
      <CodeName>HowDataProtectionAPIs_DPAPI_EnhanceSecurityInYourCMS_LiamGoldfinch-o7z2z9wp</CodeName>
      <GUID>d8755da0-9f62-4bb0-a9d6-b6a5944bed76</GUID>
      <ObjectType>cms.contentitem</ObjectType>
    </Parent>
  </ContentItemDataCommonDataID>
  <ContentItemDataGUID>7ca75c74-a7c5-49a6-b0ab-929ffaf451c1</ContentItemDataGUID>
  <LinkContentLinkType>CommunityContribution</LinkContentLinkType>
  <LinkContentMemberID>3</LinkContentMemberID>
  <LinkContentPathOrURL>
    <![CDATA[https://www.goldfinch.me/blog/how-data-protection-apis-enhance-security-in-your-cms]]>
  </LinkContentPathOrURL>
  <LinkContentPublishedDate>2025-03-18 04:00:00Z</LinkContentPublishedDate>
</contentitemdata.kenticocommunity.linkcontent>