<?xml version="1.0" encoding="utf-8"?>
<contentitemdata.kenticocommunity.imagecontent>
  <ContentItemDataCommonDataID>
    <GUID>694742fe-9df2-4c3a-ba49-f59b177b416e</GUID>
    <ObjectType>cms.contentitemcommondata</ObjectType>
    <Parent>
      <CodeName>Xk-30-00-00-content-hub-move-content-between-workspaces-ctx0naw2</CodeName>
      <GUID>f96b8a7b-901a-4b9f-9936-936ec66829c9</GUID>
      <ObjectType>cms.contentitem</ObjectType>
    </Parent>
  </ContentItemDataCommonDataID>
  <ContentItemDataGUID>b4429538-106a-41f2-956f-2176148cb4c1</ContentItemDataGUID>
  <ImageContentAsset>
    <![CDATA[{"Original":{"Identifier":"04d1562e-5862-45c0-82f1-e0536d2d09ce","Name":"xk-30-00-00-content-hub-move-content-between-workspaces.jpg","Extension":".jpg","Size":207924,"Width":1918,"Height":1078,"LastModified":"2024-12-16T19:27:15.5796234Z"},"OptimizationParameters":{"OutputExtension":"webp","Quality":80,"WidthLimit":null,"HeightLimit":null},"Variants":{"Thumbnail":{"Crop":{"IsManual":false,"X":0,"Y":2,"Width":1918,"Height":1074},"TransformationType":"Scale","Identifier":"32830ce7-364a-41dc-8a2e-7e7cec4bef05","Name":"xk-30-00-00-content-hub-move-content-between-workspaces_Thumbnail.webp","Extension":".webp","Size":0,"Width":100,"Height":56,"LastModified":"2025-09-23T02:15:47.342206Z"},"Thumbnail_Scaled":{"Crop":{"IsManual":false,"X":0,"Y":2,"Width":1918,"Height":1074},"TransformationType":"Scale","Identifier":"dc5fee34-4672-494f-baa3-2f3d865f5b06","Name":"xk-30-00-00-content-hub-move-content-between-workspaces_Thumbnail_Scaled.webp","Extension":".webp","Size":0,"Width":150,"Height":84,"LastModified":"2025-09-23T04:02:20.186886Z"},"Small_Scaled":{"Crop":{"IsManual":false,"X":0,"Y":2,"Width":1918,"Height":1074},"TransformationType":"Scale","Identifier":"0aceda0a-9046-4547-a561-6a3af59d5e9e","Name":"xk-30-00-00-content-hub-move-content-between-workspaces_Small_Scaled.webp","Extension":".webp","Size":0,"Width":400,"Height":224,"LastModified":"2025-09-23T04:02:20.186903Z"},"Medium_Scaled":{"Crop":{"IsManual":false,"X":0,"Y":1,"Width":1918,"Height":1076},"TransformationType":"Scale","Identifier":"59103616-44cb-49f0-bff2-756dd4c5c395","Name":"xk-30-00-00-content-hub-move-content-between-workspaces_Medium_Scaled.webp","Extension":".webp","Size":0,"Width":800,"Height":449,"LastModified":"2025-09-23T04:02:20.186926Z"},"Large_Scaled":{"Crop":{"IsManual":false,"X":0,"Y":1,"Width":1918,"Height":1077},"TransformationType":"Scale","Identifier":"644a2998-8a9a-4fd2-95ee-7ee56716b9f7","Name":"xk-30-00-00-content-hub-move-content-between-workspaces_Large_Scaled.webp","Extension":".webp","Size":0,"Width":1200,"Height":674,"LastModified":"2025-09-23T04:02:20.186942Z"},"Extra_Large_Scaled":{"Crop":{"IsManual":false,"X":0,"Y":0,"Width":1918,"Height":1078},"TransformationType":"Scale","Identifier":"dc6b35ea-7f7a-4ef7-8a43-770eb3056245","Name":"xk-30-00-00-content-hub-move-content-between-workspaces_Extra_Large_Scaled.webp","Extension":".webp","Size":0,"Width":1600,"Height":899,"LastModified":"2025-09-23T03:40:40.036999Z"},"Large_X2_Scaled":{"Crop":{"IsManual":false,"X":0,"Y":0,"Width":1918,"Height":1078},"TransformationType":"Scale","Identifier":"b9553adf-0544-42c2-b793-28f4f35ef7b8","Name":"xk-30-00-00-content-hub-move-content-between-workspaces_Large_X2_Scaled.webp","Extension":".webp","Size":0,"Width":1600,"Height":899,"LastModified":"2025-09-23T04:02:20.186841Z"},"Large_X3_Scaled":{"Crop":{"IsManual":false,"X":0,"Y":1,"Width":1918,"Height":1077},"TransformationType":"Scale","Identifier":"4ffc8dea-7c1a-4586-b1d7-0e1c8f84e51d","Name":"xk-30-00-00-content-hub-move-content-between-workspaces_Large_X3_Scaled.webp","Extension":".webp","Size":0,"Width":2400,"Height":1348,"LastModified":"2025-09-23T04:02:20.186843Z"}},"FocalPoint":{"X":959,"Y":539},"Identifier":"1bd2988c-1ad8-4198-8b2f-c5bcdf70562b","Name":"xk-30-00-00-content-hub-move-content-between-workspaces.webp","Extension":".webp","Size":72624,"Width":1918,"Height":1078,"LastModified":"2024-12-16T19:27:15.9053636Z"}]]>
  </ImageContentAsset>
</contentitemdata.kenticocommunity.imagecontent>