<?xml version="1.0" encoding="utf-8"?>
<contentitemdata.kenticocommunity.linkcontent>
  <ContentItemDataCommonDataID>
    <GUID>062e4025-ebec-475c-8126-88ff7d65466d</GUID>
    <ObjectType>cms.contentitemcommondata</ObjectType>
    <Parent>
      <CodeName>KenticoLexiK-wcu044bi</CodeName>
      <GUID>e93ff214-a86d-4887-8e21-0165fdd5af7f</GUID>
      <ObjectType>cms.contentitem</ObjectType>
    </Parent>
  </ContentItemDataCommonDataID>
  <ContentItemDataGUID>4fb7980e-8ef8-4310-846e-8d1cda1f00af</ContentItemDataGUID>
  <LinkContentLinkType />
  <LinkContentMemberID>0</LinkContentMemberID>
  <LinkContentPathOrURL>https://www.kentico.com/discover/lexik</LinkContentPathOrURL>
  <LinkContentPublishedDate>0001-01-01 04:57:00Z</LinkContentPublishedDate>
</contentitemdata.kenticocommunity.linkcontent>