<?xml version="1.0" encoding="utf-8"?>
<contentitemdata.kenticocommunity.blogpostcontent>
  <BlogPostContentBlogType>
    <![CDATA[[{"Identifier":"0cb21dda-384b-4792-8e1b-41034f113d28"}]]]>
  </BlogPostContentBlogType>
  <ContentItemDataCommonDataID>
    <GUID>680d809f-111f-4adc-a628-d4845a674cbe</GUID>
    <ObjectType>cms.contentitemcommondata</ObjectType>
    <Parent>
      <CodeName>XperienceByKenticoSaaSBestPractices-w75uqxkz</CodeName>
      <GUID>2e448670-eb40-4c42-bc64-dcd05054843d</GUID>
      <ObjectType>cms.contentitem</ObjectType>
    </Parent>
  </ContentItemDataCommonDataID>
  <ContentItemDataGUID>ccd8c289-b905-4cc5-8f6c-368fca834a7a</ContentItemDataGUID>
</contentitemdata.kenticocommunity.blogpostcontent>