<?xml version="1.0" encoding="utf-8"?>
<media.file>
  <FileCreatedByUserID>
    <CodeName>SeanW_kentico.com</CodeName>
    <GUID>dfbb939f-efca-409d-9ddc-613047fadcca</GUID>
    <ObjectType>cms.user</ObjectType>
  </FileCreatedByUserID>
  <FileCreatedWhen>2023-11-18 05:29:20Z</FileCreatedWhen>
  <FileDescription />
  <FileExtension>.webp</FileExtension>
  <FileGUID>bf706e94-c450-464f-9f8f-6fb0fa9c78ad</FileGUID>
  <FileImageHeight>1002</FileImageHeight>
  <FileImageWidth>1896</FileImageWidth>
  <FileLibraryID>
    <CodeName>Posts</CodeName>
    <GUID>44bc64e9-7223-447e-be49-f6fc44f779d4</GUID>
    <ObjectType>media.library</ObjectType>
  </FileLibraryID>
  <FileMimeType>image/webp</FileMimeType>
  <FileModifiedByUserID>
    <CodeName>SeanW_kentico.com</CodeName>
    <GUID>dfbb939f-efca-409d-9ddc-613047fadcca</GUID>
    <ObjectType>cms.user</ObjectType>
  </FileModifiedByUserID>
  <FileName>
    <![CDATA[xperience-by-kentico-v28-00-00-dancing-goat-html-attribute-rich-text-allowed-list]]>
  </FileName>
  <FilePath>
    <![CDATA[xperience-by-kentico-v28-00-00-dancing-goat-html-attribute-rich-text-allowed-list.webp]]>
  </FilePath>
  <FileSize>57840</FileSize>
  <FileTitle />
</media.file>