<?xml version="1.0" encoding="utf-8"?>
<contentitemdata.kenticocommunity.blogpostpage>
  <BlogPostPageAuthorContent>
    <![CDATA[[{"Identifier":"f9ac36a5-e1a6-4d21-9cb7-beb385d0fea0"}]]]>
  </BlogPostPageAuthorContent>
  <BlogPostPageBlogPostContent>
    <![CDATA[[{"Identifier":"283d4fdd-4075-4e6c-83ff-04f7492a0ec9"}]]]>
  </BlogPostPageBlogPostContent>
  <BlogPostPageBlogType>
    <![CDATA[[{"Identifier":"0cb21dda-384b-4792-8e1b-41034f113d28"}]]]>
  </BlogPostPageBlogType>
  <BlogPostPagePublishedDate>2025-02-11 01:01:00Z</BlogPostPagePublishedDate>
  <BlogPostPageQAndAQuestionPages>
    <![CDATA[[{"Identifier":"bb8d8616-d1fe-48d3-83c5-6f310cec0951"}]]]>
  </BlogPostPageQAndAQuestionPages>
  <ContentItemDataCommonDataID>
    <GUID>8e62cc6a-f9b1-409f-a0c6-2f89729f7e17</GUID>
    <ObjectType>cms.contentitemcommondata</ObjectType>
    <Parent>
      <CodeName>UsingPersonalizationToDriveMembershipGrowth-ybfnchvt</CodeName>
      <GUID>cd42e551-3ac7-4b71-ace1-d794628e11d8</GUID>
      <ObjectType>cms.contentitem</ObjectType>
    </Parent>
  </ContentItemDataCommonDataID>
  <ContentItemDataGUID>449f6cba-8fe4-4e5f-b3d4-3240e64088ec</ContentItemDataGUID>
</contentitemdata.kenticocommunity.blogpostpage>