<?xml version="1.0" encoding="utf-8"?>
<cms.webpageurlpath>
  <WebPageUrlPath>
    <![CDATA[Q-and-A/q/Blog-Discussion-Xperience-by-Kentico-Refresh-April-17-2025-75d83762]]>
  </WebPageUrlPath>
  <WebPageUrlPathContentLanguageID>
    <CodeName>en-US</CodeName>
    <GUID>6c743a9e-8a63-425b-bef6-756c12c1bbf5</GUID>
    <ObjectType>cms.contentlanguage</ObjectType>
  </WebPageUrlPathContentLanguageID>
  <WebPageUrlPathGUID>fbd3a91e-a2e3-4889-8545-4eeef16a17e7</WebPageUrlPathGUID>
  <WebPageUrlPathHash>
    <![CDATA[0194192E2FB65E563566A98EF1E6724CACBD705FA9C27F8F125FD2E87875CB11]]>
  </WebPageUrlPathHash>
  <WebPageUrlPathIsCanonical>True</WebPageUrlPathIsCanonical>
  <WebPageUrlPathIsDraft>False</WebPageUrlPathIsDraft>
  <WebPageUrlPathIsLatest>True</WebPageUrlPathIsLatest>
  <WebPageUrlPathType>0</WebPageUrlPathType>
  <WebPageUrlPathWebPageItemID>
    <CodeName>Blog-Discussion-Xperience-by-Kentico-Refresh-April-17-2025-75d83762-dmkm94g8</CodeName>
    <GUID>97d52e3e-8f11-41fe-aa0f-52d67b22a310</GUID>
    <ObjectType>cms.webpageitem</ObjectType>
  </WebPageUrlPathWebPageItemID>
  <WebPageUrlPathWebsiteChannelID>
    <GUID>9ca57e0f-969f-43be-91d3-6c45659316bd</GUID>
    <ObjectType>cms.websitechannel</ObjectType>
    <Parent>
      <CodeName>devnet</CodeName>
      <GUID>4f636110-fd4a-4905-83e6-998752c2b2c2</GUID>
      <ObjectType>cms.channel</ObjectType>
    </Parent>
  </WebPageUrlPathWebsiteChannelID>
</cms.webpageurlpath>