<?xml version="1.0" encoding="utf-8"?>
<cms.contentitem>
  <ContentItemContentTypeID>
    <CodeName>KenticoCommunity.LinkContent</CodeName>
    <GUID>05bcb412-2000-455b-95fd-74dad14fbdae</GUID>
    <ObjectType>cms.contenttype</ObjectType>
  </ContentItemContentTypeID>
  <ContentItemGUID>c2b298c7-9a2a-47c5-9317-c2f6db920e14</ContentItemGUID>
  <ContentItemIsReusable>True</ContentItemIsReusable>
  <ContentItemIsSecured>False</ContentItemIsSecured>
  <ContentItemName>XperienceByKenticoGitHubList-5popcckk</ContentItemName>
</cms.contentitem>